gryibwc/__init__.py
gryibwc/gryibwc.py
gryibwc-0.9.4.dist-info/LICENSE
gryibwc-0.9.4.dist-info/METADATA
gryibwc-0.9.4.dist-info/WHEEL
gryibwc-0.9.4.dist-info/entry_points.txt
gryibwc-0.9.4.dist-info/top_level.txt
gryibwc-0.9.4.dist-info/RECORD
